[{"bbox": [195, 192, 1454, 1059], "category": "Table", "text": "<table><tr><td></td><td>loss account, after deducting the aggregate value of the accumulated losses, deferred expenditure and miscellaneous expenditure not written off, as per the Restated Financial Information</td></tr><tr><td>Current Ratio</td><td>Current ratio means current assets divided by current liabilities</td></tr><tr><td>Total Debt / Equity</td><td>Total debt /Equity is calculated as total debt /net worth</td></tr><tr><td>Debt Service Coverage Ratio</td><td>Debt service coverage is defined as profit after tax + non-cash expenses + finance cost/interest expenses +principal repayment +lease payment</td></tr><tr><td>ROE</td><td>ROE is calculated as profit after tax /average total net worth</td></tr><tr><td>ROCE</td><td>ROCE is calculated as profit before tax plus Interest cost /Capital Employed. Capital employed will be calculated as sum of Net Worth and Total Debt reducing Deferred Tax liability</td></tr><tr><td>Inventory turnover ratio</td><td>Inventory Turnover Ratio is calculated by dividing cost of goods sold during the period with average inventory. Inventory will exclude Packing material and stores & spares</td></tr><tr><td>Trade Receivables turnover ratio</td><td>Trade Receivables Turnover Ratio is calculated by dividing Credit Sales during the period with average receivables</td></tr><tr><td>Trade payables turnover ratio</td><td>Trade Payables Turnover Ratio for calculated by dividing Credit purchases during the period with average payables</td></tr><tr><td>Working Capital Turnover Ratio</td><td>Working capital turnover ratio defined as revenue from operations divided by average working capital. Working capital will be calculated as Current Assets -Current liabilities</td></tr><tr><td>Fixed Assets Turnover Ratio</td><td>Fixed Asset Turnover is calculated as total revenue from operations divided by average net fixed assets excluding Capital work in Progress.</td></tr><tr><td>Installed Capacity in M.T. (Ginning Division)</td><td>Installed Capacity in M.T. (Ginning Division) is calculated as total production capacity of (Ginning Division)</td></tr><tr><td>Installed Capacity in M.T. (Spinning Division)</td><td>Installed Capacity in M.T. (Spinning Division) is calculated as total production capacity of (Spinning Division)</td></tr><tr><td>Utilised Capacity M.T. (Ginning Division)</td><td>Utilized Capacity in M.T. (Ginning Division) is calculated as total production of (Ginning Division)</td></tr><tr><td>Utilised Capacity M.T. (Spinning Division)</td><td>Utilized Capacity in M.T. (Spinning Division) is calculated as total production of (Spinning Division)</td></tr></table>"}, {"bbox": [812, 2267, 839, 2291], "category": "Page-footer", "text": "14"}]