[{"bbox": [135, 161, 1567, 226], "category": "Text", "text": "Profit after tax for period ended on March 31, 2025 stood at ₹ 840.74 lakhs. During this period, our Company recorded Profit after tax margin of 13.53% of Total Income."}, {"bbox": [135, 257, 1373, 290], "category": "Section-header", "text": "## Main Components of our Profit and Loss Account (Based on Restated Standalone Financial Statements)"}, {"bbox": [135, 322, 305, 351], "category": "Section-header", "text": "**Total Income:**"}, {"bbox": [135, 355, 1567, 414], "category": "Text", "text": "Our total income was ₹ 6,081.76 lakhs for the period ended on March 31, 2025 which comprises of revenue from operations and other income."}, {"bbox": [135, 450, 446, 481], "category": "Section-header", "text": "**Revenue from operations:**"}, {"bbox": [135, 481, 1567, 545], "category": "Text", "text": "Our revenue from operations was ₹ 6,073.11 lakhs for the period ended on March 31, 2025 constituting 99.86% of our Total Income mainly consists of revenue generated from Sale of Goods."}, {"bbox": [135, 578, 313, 607], "category": "Section-header", "text": "**Other Income:**"}, {"bbox": [135, 609, 1567, 674], "category": "Text", "text": "Our other income was ₹ 8.65 lakhs for the period ended on March 31, 2025 constituting 0.14% of our Total Income comprises of interest on fixed deposit and other non-operating income."}, {"bbox": [135, 707, 326, 736], "category": "Section-header", "text": "**Total Expenses:**"}, {"bbox": [135, 738, 1567, 833], "category": "Text", "text": "Our Company's Total Expenses for the period ended on March 31, 2025 was ₹ 5,285.61 lakhs constituting 86.91% of our Total Income. Total Expenses comprise of Cost of Material Consumed, Employee benefits expense, Finance costs, Depreciation and Amortization expenses and Other expenses."}, {"bbox": [135, 833, 472, 863], "category": "Section-header", "text": "**Cost of material Consumed:**"}, {"bbox": [135, 865, 1567, 929], "category": "Text", "text": "Our Company's Cost of materials consumed for the period ended on March 31, 2025 was ₹ 4,339.14 lakhs constituting 71.35% of our Total Income which includes Purchases and Direct expenses."}, {"bbox": [135, 961, 463, 992], "category": "Section-header", "text": "**Employee benefits expense:**"}, {"bbox": [135, 992, 1567, 1089], "category": "Text", "text": "Our employee benefits expense for the period ended on March 31, 2025 was ₹ 99.41 lakhs constituting 1.63% of Total Income. Employee benefits expense primarily comprises of Salaries, Contribution to Provident and other funds and Staff Welfare Expenses."}, {"bbox": [135, 1120, 313, 1149], "category": "Section-header", "text": "**Finance Costs:**"}, {"bbox": [135, 1151, 1567, 1216], "category": "Text", "text": "Our Finance cost for the period ended on March 31, 2025 was ₹ 70.90 lakhs constituting 1.17% of Total Income. Finance cost comprises of Interest expenses."}, {"bbox": [135, 1249, 633, 1279], "category": "Section-header", "text": "**Depreciation and Amortization Expenses:**"}, {"bbox": [135, 1279, 1567, 1377], "category": "Text", "text": "Depreciation & Amortization expenses for the period ended on March 31, 2025 was ₹ 31.91 lakhs constituting 0.52% of Total Income. Depreciation & Amortization expense comprises of depreciation on Computer, Plant and Equipment, Furniture and Fixtures, Vehicles, Office Equipment and Other Intangible Assets."}, {"bbox": [135, 1409, 334, 1439], "category": "Section-header", "text": "**Other Expenses:**"}, {"bbox": [135, 1439, 1567, 1695], "category": "Text", "text": "Other expenses for the period ended on March 31, 2025 was ₹ 744.25 lakhs constituting 12.24% of Total Income. Other expenses mainly comprise of Rent Rates & Taxes (₹ 49.75 lakhs constituting 0.82%), Auditors Remuneration (₹ 2.50 lakhs constituting 0.04%), Bank Charges (₹ 8.49 lakhs constituting 0.14%), Discount expenses (₹ 20.13 lakhs constituting 0.33%), Business Promotion Expenses (₹ 23.34 lakhs constituting 0.38%), Printing and Stationery (₹ 6.24 lakhs constituting 0.10%) and Travelling and Transportation expenses (₹ 239.08 lakhs constituting 3.93%), Foreign exchange gain and loss (₹ 6.28 lakhs constituting 0.10%), Warehouse Expenses (₹ 149.92 lakhs constituting 2.47%), legal & Professional Fees (₹ 175.18 lakhs constituting 2.88%), Insurance expenses (₹ 1.21 lakhs constituting 0.02%), Selling and Distribution (₹ 31.62 lakhs constituting 0.52%) and Other Expenses (₹ 30.50 lakhs constituting 0.50%) of total income."}, {"bbox": [135, 1727, 422, 1758], "category": "Section-header", "text": "**Profit before tax (PBT):**"}, {"bbox": [135, 1758, 1567, 1823], "category": "Text", "text": "Profit before tax for period ended on March 31, 2025 stood at ₹ 796.15 lakhs. During this period, our Company recorded Profit before tax margin of 13.09% of Total Income."}, {"bbox": [135, 1855, 406, 1886], "category": "Section-header", "text": "**Profit after tax (PAT):**"}, {"bbox": [135, 1886, 1567, 1951], "category": "Text", "text": "Profit after tax for period ended on March 31, 2025 stood at ₹ 802.03 lakhs. During this period, our Company recorded Profit after tax margin of 13.19% of Total Income."}, {"bbox": [135, 1983, 1302, 2014], "category": "Section-header", "text": "## Comparison of FY 2024-25 with FY 2023-24 (Based on Restated Standalone Financial Statements)"}, {"bbox": [135, 2047, 305, 2076], "category": "Section-header", "text": "**Total Income:**"}, {"bbox": [827, 2171, 875, 2202], "category": "Page-footer", "text": "224"}]