[{"bbox": [86, 168, 1157, 192], "category": "Section-header", "text": "OM POWER TRANSMISSION LIMITED (formerly known as OM POWER TRANSMISSION PRIVATE LIMITED)"}, {"bbox": [86, 194, 374, 215], "category": "Section-header", "text": "Restated Financial Information"}, {"bbox": [86, 219, 466, 243], "category": "Section-header", "text": "Restated Statement Of Changes in Equity"}, {"bbox": [86, 245, 532, 268], "category": "Text", "text": "(All amounts in INR Lakhs, unless otherwise stated)"}, {"bbox": [86, 295, 307, 319], "category": "Section-header", "text": "a. Equity Share capital"}, {"bbox": [83, 318, 1581, 444], "category": "Table", "text": "<table><thead><tr><th>Particulars</th><th>As at<br>March 31, 2025</th><th>As at<br>March 31, 2024</th><th>As at<br>March 31, 2023</th></tr></thead><tbody><tr><td>Balance at the Beginning of the year</td><td>60.00</td><td>60.00</td><td>60.00</td></tr><tr><td><strong>Balance at the end of the year</strong></td><td><strong>60.00</strong></td><td><strong>60.00</strong></td><td><strong>60.00</strong></td></tr></tbody></table>"}, {"bbox": [86, 469, 231, 492], "category": "Section-header", "text": "b. Other Equity"}, {"bbox": [83, 491, 1321, 1064], "category": "Table", "text": "<table><thead><tr><th rowspan=\"2\">Particulars</th><th>Reserves and Surplus</th><th rowspan=\"2\">Total</th></tr><tr><th>Retained Earnings</th></tr></thead><tbody><tr><td><strong>Balance at April 1, 2022</strong></td><td><strong>3,823.86</strong></td><td><strong>3,823.86</strong></td></tr><tr><td>Net Profit for the year</td><td>623.72</td><td>623.72</td></tr><tr><td>Other Comprehensive Income for the year (Net of Tax)</td><td>(0.85)</td><td>(0.85)</td></tr><tr><td>Items of other comprehensive income recognised in retained earning (net of tax)</td><td>(170.60)</td><td>(170.60)</td></tr><tr><td>Total Comprehensive Income for the year</td><td>4,276.13</td><td>4,276.13</td></tr><tr><td><strong>Balance at March 31, 2023</strong></td><td><strong>4,276.13</strong></td><td><strong>4,276.13</strong></td></tr><tr><td><strong>Balance at April 1, 2023</strong></td><td><strong>4,276.13</strong></td><td><strong>4,276.13</strong></td></tr><tr><td>Net Profit for the year</td><td>741.24</td><td>741.24</td></tr><tr><td>Other Comprehensive Income for the year (Net of Tax)</td><td>(13.72)</td><td>(13.72)</td></tr><tr><td>Total Comprehensive Income for the year</td><td>5,003.65</td><td>5,003.65</td></tr><tr><td><strong>Balance at March 31, 2024</strong></td><td><strong>5,003.65</strong></td><td><strong>5,003.65</strong></td></tr><tr><td><strong>Balance at April 1, 2024</strong></td><td><strong>5,003.65</strong></td><td><strong>5,003.65</strong></td></tr><tr><td>Net Profit for the year</td><td>2,208.48</td><td>2,208.48</td></tr><tr><td>Other Comprehensive Income for the year (Net of Tax)</td><td>(6.71)</td><td>(6.71)</td></tr><tr><td>Total Comprehensive Income for the year</td><td>7,205.42</td><td>7,205.42</td></tr><tr><td><strong>Balance at March 31, 2025</strong></td><td><strong>7,205.42</strong></td><td><strong>7,205.42</strong></td></tr></tbody></table>"}, {"bbox": [86, 1092, 252, 1112], "category": "Section-header", "text": "Nature of reserve:"}, {"bbox": [86, 1115, 282, 1139], "category": "Section-header", "text": "i) Retained Earnings:"}, {"bbox": [86, 1141, 1479, 1166], "category": "Text", "text": "Retained earnings represents the accumulated profits / losses made by the Company over the years, and includes remeasurement gains/ loss on defined benefit plan."}, {"bbox": [86, 1192, 1499, 1217], "category": "Text", "text": "The above Restated financial Statement of equity should be read with the accompanying notes 1-60 form an integral part of restated financial information."}, {"bbox": [86, 1218, 959, 1242], "category": "Text", "text": "This is the Restated Statement of Changes in Equity referred to in our Examination report of even date."}, {"bbox": [86, 1269, 367, 1291], "category": "Text", "text": "As Per our report of even date."}, {"bbox": [86, 1332, 337, 1407], "category": "Text", "text": "For O.M.M.S & Associates\nChartered Accountants\nFirm Regn. No. 135149W"}, {"bbox": [86, 1435, 310, 1510], "category": "Text", "text": "Chintan R Oza\nPartner\nMembership No. 147132"}, {"bbox": [86, 1538, 320, 1587], "category": "Text", "text": "Place : Ahmedabad\nDate: September 29, 2025"}, {"bbox": [813, 1332, 1244, 1355], "category": "Text", "text": "For, OM POWER TRANSMISSION LIMITED"}, {"bbox": [813, 1435, 986, 1561], "category": "Text", "text": "Kanubhai Patel\nManaging Director\nDIN: 03522537\nPlace : Ahmedabad\nDate: September 29, 2025"}, {"bbox": [1070, 1435, 1375, 1561], "category": "Text", "text": "Kalpeshbhai Patel\nChairman and Executive Director\nDIN: 03516312\nPlace : Ahmedabad\nDate: September 29, 2025"}, {"bbox": [813, 1615, 1044, 1742], "category": "Text", "text": "Hardik Patel\nCompany Secretary\nPlace : Ahmedabad\nMembership No: A55828\nDate: September 29, 2025"}, {"bbox": [1070, 1615, 1302, 1742], "category": "Text", "text": "Chetan Modi\nChief Financial Officer\nPlace : Ahmedabad\nDate: September 29, 2025"}, {"bbox": [826, 2101, 869, 2127], "category": "Page-footer", "text": "297"}]