[{"bbox": [155, 154, 1494, 2156], "category": "Table", "text": "<table><thead><tr><td>Term</td><td>Description</td></tr></thead><tbody><tr><td></td><td>the websites of BSE and NSE, as updated from time to time.</td></tr><tr><td>Collecting Registrar and Share Transfer Agents/ CRTAs/ RTAs</td><td>Registrar and share transfer agents registered with SEBI and eligible to procure Bids at the Designated RTA Locations in terms of, among others, SEBI circular no. CIR/CFD/POLICYCELL/11/2015 dated November 10, 2015, issued by SEBI.</td></tr><tr><td>Cut-off Price</td><td>Offer Price, finalised by our Company, in consultation with the BRLM, which shall be any price within the Price Band.<br/>Only Retail Individual Investors are entitled to Bid at the Cut-off Price. QIBs (including Anchor Investors) and Non-Institutional Investors are not entitled to Bid at the Cut-off Price.</td></tr><tr><td>Demographic Details</td><td>Details of the Bidders including the Bidder's address, name of the Bidder's father/husband, investor status, occupation and bank account details and UPI ID, where applicable.</td></tr><tr><td>Designated CDP Locations</td><td>Such locations of the CDPs where Bidders (other than Anchor Investors) can submit the ASBA Forms. The details of such Designated CDP Locations, along with names and contact details of the Collecting Depository Participants eligible to accept ASBA Forms are available on the respective websites of the Stock Exchanges (www.bseindia.com and www.nseindia.com).</td></tr><tr><td>Designated Date</td><td>The date on which funds are transferred from the Escrow Account(s) and the amounts blocked are transferred from the ASBA Accounts, as the case may be, to the Public Offer Account(s) or the Refund Account(s), as appropriate, in terms of the Red Herring Prospectus and the Prospectus, after the finalisation of the Basis of Allotment in consultation with the Designated Stock Exchange, following which Equity Shares may be Allotted to successful Bidders in the Offer.</td></tr><tr><td>Designated Intermediaries</td><td>Collectively, the members of the Syndicate, sub-syndicate or agents, SCSBs (other than in relation to RIBs using the UPI Mechanism), Registered Brokers, CDPs and RTAs, who are authorised to collect Bid cum Application Forms from the relevant Bidders, in relation to the Offer.<br/>In relation to ASBA Forms submitted by RIBs Bidding in the Retail Portion by authorising an SCSB to block the Bid Amount in the ASBA Account, Designated Intermediaries shall mean SCSBs.<br/>In relation to ASBA Forms submitted by UPI Bidders where the Bid Amount will be blocked upon acceptance of UPI Mandate Request by such UPI Bidder using the UPI Mechanism, Designated Intermediaries shall mean Syndicate, sub-syndicate/agents, Registered Brokers, CDPs, SCSBs and RTAs.<br/>In relation to ASBA Forms submitted by QIBs and Non-Institutional Bidders (not using the UPI Mechanism), Designated Intermediaries shall mean Syndicate, sub-syndicate/ agents, SCSBs, Registered Brokers, the CDPs and RTAs</td></tr><tr><td>Designated RTA Locations</td><td>Such locations of the CRTAs where Bidders (other than Anchor Investors) can submit the ASBA Forms to CRTAs.<br/>The details of such Designated CRTA Locations, along with names and contact details of the CRTAs eligible to accept ASBA Forms are available on the respective websites of the Stock Exchanges (www.bseindia.com and www.nseindia.com) and updated from time to time.</td></tr><tr><td>Designated SCSB Branches</td><td>Such branches of the SCSBs which shall collect the ASBA Forms, a list of which is available on the website of SEBI at www.sebi.gov.in/sebiweb/other/OtherAction.do?doRecognised=yes or at such other website as may be prescribed by SEBI from time to time.</td></tr><tr><td>Designated Stock Exchange</td><td>[●]</td></tr><tr><td>Draft Red Herring Prospectus/ DRHP</td><td>This draft red herring prospectus dated September 30, 2025 issued in accordance with the SEBI ICDR Regulations, which does not contain complete particulars of the price at which the Equity Shares will be Allotted and the size of the Offer including any addenda or corrigenda thereto.</td></tr><tr><td>Eligible FPI(s)</td><td>FPI(s) that are eligible to participate in the Offer in terms of applicable law and from</td></tr></tbody></table>"}, {"bbox": [814, 2203, 837, 2236], "category": "Page-footer", "text": "6"}]