[{"bbox": [91, 99, 367, 130], "category": "Page-header", "text": "Q-Line Biotech Limited"}, {"bbox": [91, 170, 1344, 202], "category": "List-item", "text": "11. List of Shareholders of the Company holding 1% or more of the paid-up Share Capital of the Company:"}, {"bbox": [130, 233, 908, 266], "category": "List-item", "text": "a) As on the date of filing of this Draft Red Herring Prospectus: -"}, {"bbox": [91, 293, 1544, 594], "category": "Table", "text": "<table><thead><tr><th>Sr. No.</th><th>Names of Shareholders</th><th>Shares held (Face Value of Rs. 10 each)</th><th>% Pre-Issue paid up Share Capital</th></tr></thead><tbody><tr><td>1.</td><td>Saurabh Garg</td><td>1,01,91,000</td><td>62.62</td></tr><tr><td>2.</td><td>Amita Garg</td><td>39,37,480</td><td>24.19</td></tr><tr><td>3.</td><td>Ajay Kumar Mahanty</td><td>7,50,000</td><td>4.61</td></tr><tr><td>4.</td><td>Abhay Agrawal</td><td>7,56,010</td><td>4.65</td></tr><tr><td>5.</td><td>Alok Kumar Agarwal</td><td>2,09,400</td><td>1.29</td></tr><tr><td></td><td><strong>Total</strong></td><td><strong>1,58,43,890</strong></td><td><strong>97.35</strong></td></tr></tbody></table>"}, {"bbox": [130, 627, 1037, 660], "category": "List-item", "text": "b) Ten days prior to the date of filing of this Draft Red Herring Prospectus: -"}, {"bbox": [91, 688, 1557, 956], "category": "Table", "text": "<table><thead><tr><th>Sr. No.</th><th>Names of Shareholders</th><th>Shares held (Face Value of ` 10 each)</th><th>% Pre-Issue paid up Share Capital</th></tr></thead><tbody><tr><td>1.</td><td>Saurabh Garg</td><td>1,01,37,000</td><td>64.36</td></tr><tr><td>2.</td><td>Amita Garg</td><td>39,37,480</td><td>25.00</td></tr><tr><td>3.</td><td>Ajay Kumar Mahanty</td><td>7,50,000</td><td>4.76</td></tr><tr><td>4.</td><td>Abhay Agrawal</td><td>7,56,010</td><td>4.80</td></tr><tr><td></td><td><strong>Total</strong></td><td><strong>1,55,80,490</strong></td><td><strong>98.92</strong></td></tr></tbody></table>"}, {"bbox": [130, 988, 1041, 1021], "category": "List-item", "text": "c) One Year prior to the date of filing of this Draft Red Herring Prospectus: -"}, {"bbox": [91, 1049, 1557, 1284], "category": "Table", "text": "<table><thead><tr><th>Sr. No.</th><th>Names of Shareholders</th><th>Shares held (Face Value of ` 10 each)</th><th>% Pre-Issue paid up Share Capital</th></tr></thead><tbody><tr><td>1.</td><td>Saurabh Garg</td><td>10,19,999</td><td>64.76</td></tr><tr><td>2.</td><td>Amita Garg</td><td>4,72,498</td><td>30.00</td></tr><tr><td>3.</td><td>Ajay Kumar Mahanty</td><td>75,000</td><td>4.76</td></tr><tr><td></td><td><strong>Total</strong></td><td><strong>15,67,497</strong></td><td><strong>99.52</strong></td></tr></tbody></table>"}, {"bbox": [130, 1317, 1056, 1350], "category": "List-item", "text": "d) Two Years prior to the date of filing of this Draft Red Herring Prospectus: -"}, {"bbox": [91, 1378, 1557, 1612], "category": "Table", "text": "<table><thead><tr><th>Sr. No.</th><th>Names of Shareholders</th><th>Shares held (Face Value of ` 10 each)</th><th>% Pre-Issue paid up Share Capital</th></tr></thead><tbody><tr><td>1.</td><td>Saurabh Garg</td><td>10,20,000</td><td>64.76</td></tr><tr><td>2.</td><td>Amita Garg</td><td>4,72,500</td><td>30.00</td></tr><tr><td>3.</td><td>Ajay Kumar Mahanty</td><td>75,000</td><td>4.76</td></tr><tr><td></td><td><strong>Total</strong></td><td><strong>15,67,500</strong></td><td><strong>99.52</strong></td></tr></tbody></table>"}, {"bbox": [91, 1644, 1557, 1709], "category": "List-item", "text": "12. Our Company has not made any Initial Public Offer of specified securities in the preceding two years from the date of filing of this Draft Red Herring Prospectus."}, {"bbox": [91, 1740, 1557, 2061], "category": "List-item", "text": "13. Except for the allotment of equity shares pursuant to the Pre-IPO Placement, if any, there will be no further issue of capital, whether by way of issue of bonus shares, preferential allotment, Right issue or in any other manner during the period commencing from the date of the Draft Red Herring Prospectus until the Equity Shares of our Company have been listed or application money unblocked on account of failure of Issue. Further, our Company does not intend to alter its capital structure within six months from the date of opening of the issue, by way of split / consolidation of the denomination of Equity Shares. However, our Company may further issue Equity shares (including issue of securities convertible into Equity Shares) whether preferential or otherwise after the date of the listing of equity shares to finance an acquisition, merger or joint venture or for regulatory compliance or such other scheme of arrangement or any other purpose as the Board of Directors may deem fit, if an opportunity of such nature is determined by the Board of Directors to be in the interest of our Company."}, {"bbox": [91, 2092, 922, 2125], "category": "List-item", "text": "14. Capital Buildup in respect of Shareholding of our Promoters"}, {"bbox": [810, 2171, 840, 2200], "category": "Page-footer", "text": "78"}]