[{"bbox": [49, 42, 585, 64], "category": "Page-header", "text": "Duroflex Limited (formerly known as Duroflex Private Limited)"}, {"bbox": [49, 69, 777, 91], "category": "Page-header", "text": "Annexure VII - Notes to the Restated Consolidated Financial Information (continued)"}, {"bbox": [49, 95, 810, 117], "category": "Page-header", "text": "(All amounts are in Rs. million, except share data and per share data, unless otherwise stated)"}, {"bbox": [49, 147, 289, 169], "category": "Section-header", "text": "39 Income-tax (continued)"}, {"bbox": [89, 199, 1447, 222], "category": "Section-header", "text": "(f) The following table provides the details of income tax assets and income tax liabilities as of 30 June 2025, 31 March 2025, 31 March 2024 and 31 March 2023"}, {"bbox": [87, 222, 1654, 365], "category": "Table", "text": "<table><thead><tr><th>Particulars</th><th>As at<br>30 June 2025</th><th>As at<br>31 March 2025</th><th>As at<br>31 March 2024</th><th>As at<br>31 March 2023</th></tr></thead><tbody><tr><td>Income tax assets (net)</td><td>64.64</td><td>127.97</td><td>155.96</td><td>21.69</td></tr><tr><td>Current tax liabilities (net)</td><td>2.53</td><td>1.95</td><td>0.30</td><td>28.45</td></tr><tr><td><strong>Net current income tax asset / (liability)</strong></td><td><strong>62.11</strong></td><td><strong>126.02</strong></td><td><strong>155.66</strong></td><td><strong>(6.76)</strong></td></tr></tbody></table>"}, {"bbox": [89, 391, 1556, 414], "category": "Section-header", "text": "(g) The gross movement in the current income tax asset / (liability) for the period / year ended 30 June 2025, 31 March 2025, 31 March 2024 and 31 March 2023 is as follows."}, {"bbox": [87, 414, 1654, 635], "category": "Table", "text": "<table><thead><tr><th>Particulars</th><th>As at<br>30 June 2025</th><th>As at<br>31 March 2025</th><th>As at<br>31 March 2024</th><th>As at<br>31 March 2023</th></tr></thead><tbody><tr><td><strong>Net current income tax asset / (liability) at the beginning</strong></td><td>126.02</td><td>155.66</td><td>(6.76)</td><td>91.71</td></tr><tr><td>Income tax paid, net of refund</td><td>(32.04)</td><td>34.40</td><td>167.56</td><td>59.30</td></tr><tr><td>Current income tax expense</td><td>(34.69)</td><td>(64.04)</td><td>(5.14)</td><td>(155.39)</td></tr><tr><td>Interest on income tax</td><td>-</td><td>-</td><td>-</td><td>(3.00)</td></tr><tr><td>Income tax on other comprehensive income and others</td><td>2.82</td><td>-</td><td>-</td><td>0.62</td></tr><tr><td><strong>Net current income tax asset / (liability) at the end</strong></td><td><strong>62.11</strong></td><td><strong>126.02</strong></td><td><strong>155.66</strong></td><td><strong>(6.76)</strong></td></tr></tbody></table>"}, {"bbox": [89, 662, 402, 685], "category": "Section-header", "text": "(h) Unrecognised deferred tax assets"}, {"bbox": [89, 688, 707, 710], "category": "Text", "text": "Tax losses for which no deferred tax asset was recognised expire as follows :"}, {"bbox": [87, 712, 1654, 884], "category": "Table", "text": "<table><thead><tr><th>Particulars</th><th>As at<br>30 June 2025</th><th>As at<br>31 March 2025</th><th>As at<br>31 March 2024</th><th>As at<br>31 March 2023</th></tr></thead><tbody><tr><td>Carry forward business losses</td><td>114.50</td><td>129.89</td><td>609.90</td><td>841.8</td></tr><tr><td>Expiry (in years)</td><td>2029-31</td><td>2029-31</td><td>2029-31</td><td>2029-31</td></tr><tr><td>Unabsorbed depreciation</td><td>238.50</td><td>239.49</td><td>240.33</td><td>242.36</td></tr><tr><td>Expiry (in years)</td><td>indefinite</td><td>indefinite</td><td>indefinite</td><td>indefinite</td></tr></tbody></table>"}, {"bbox": [657, 989, 1044, 1012], "category": "Text", "text": "< This space has been intentionally left blank >"}, {"bbox": [830, 2128, 864, 2151], "category": "Page-footer", "text": "325"}]