[{"bbox": [498, 80, 1151, 139], "category": "Section-header", "text": "# ECO Fuel Systems (India) Limited\n(Formerly known as ECO Fuel Systems (India) Private Limited)"}, {"bbox": [511, 163, 1136, 183], "category": "Section-header", "text": "## Notes to Ind AS Restated Consolidated Financial Statements"}, {"bbox": [1424, 186, 1599, 204], "category": "Text", "text": "(Amount in Rs. Lakhs)"}, {"bbox": [49, 229, 241, 246], "category": "Section-header", "text": "## 20. TRADE PAYABLES"}, {"bbox": [76, 268, 1445, 405], "category": "Table", "text": "<table><thead><tr><th>Particulars</th><th>As at<br>31-Mar-25</th><th>As at<br>31-Mar-24</th><th>As at<br>31-Mar-23</th></tr></thead><tbody><tr><td>Dues to micro and small enterprises</td><td>38.69</td><td>20.41</td><td>31.02</td></tr><tr><td>Due to others</td><td>235.41</td><td>813.13</td><td>516.91</td></tr><tr><td></td><td>274.10</td><td>833.54</td><td>547.93</td></tr></tbody></table>"}, {"bbox": [81, 428, 298, 447], "category": "Section-header", "text": "### Aging of Trade Payables:"}, {"bbox": [81, 449, 254, 467], "category": "Text", "text": "As at March 31, 2025:"}, {"bbox": [76, 488, 1601, 689], "category": "Table", "text": "<table><thead><tr><th rowspan=\"2\">Particulars</th><th colspan=\"4\">Outstanding for following periods from date of transaction</th><th rowspan=\"2\">Total</th></tr><tr><th>Less than<br>1 year</th><th>1 - 2 years</th><th>2 - 3 years</th><th>More than 3<br>years</th></tr></thead><tbody><tr><td>Undisputed dues - MSME</td><td>38.69</td><td>-</td><td>-</td><td>-</td><td>38.69</td></tr><tr><td>Undisputed dues - Others</td><td>211.67</td><td>18.89</td><td>4.84</td><td>-</td><td>235.41</td></tr><tr><td>Disputed dues - MSME</td><td>-</td><td>-</td><td>-</td><td>-</td><td>-</td></tr><tr><td>Disputed dues - Others</td><td>-</td><td>-</td><td>-</td><td>-</td><td>-</td></tr><tr><td></td><td>250.36</td><td>18.89</td><td>4.84</td><td>-</td><td>274.10</td></tr></tbody></table>"}, {"bbox": [81, 712, 254, 729], "category": "Text", "text": "As at March 31, 2024:"}, {"bbox": [76, 749, 1601, 943], "category": "Table", "text": "<table><thead><tr><th rowspan=\"2\">Particulars</th><th colspan=\"4\">Outstanding for following periods from date of transaction</th><th rowspan=\"2\">Total</th></tr><tr><th>Less than<br>1 year</th><th>1 - 2 years</th><th>2 - 3 years</th><th>More than 3<br>years</th></tr></thead><tbody><tr><td>Undisputed dues - MSME</td><td>20.41</td><td>-</td><td>-</td><td>-</td><td>20.41</td></tr><tr><td>Undisputed dues - Others</td><td>719.14</td><td>63.96</td><td>30.03</td><td>-</td><td>813.13</td></tr><tr><td>Disputed dues - MSME</td><td>-</td><td>-</td><td>-</td><td>-</td><td>-</td></tr><tr><td>Disputed dues - Others</td><td>-</td><td>-</td><td>-</td><td>-</td><td>-</td></tr><tr><td></td><td>739.55</td><td>63.96</td><td>30.03</td><td>-</td><td>833.54</td></tr></tbody></table>"}, {"bbox": [81, 967, 254, 985], "category": "Text", "text": "As at March 31, 2023:"}, {"bbox": [76, 1005, 1601, 1179], "category": "Table", "text": "<table><thead><tr><th rowspan=\"2\">Particulars</th><th colspan=\"4\">Outstanding for following periods from date of transaction</th><th rowspan=\"2\">Total</th></tr><tr><th>Less than<br>1 year</th><th>1 - 2 years</th><th>2 - 3 years</th><th>More than 3<br>years</th></tr></thead><tbody><tr><td>Undisputed dues - MSME</td><td>31.02</td><td>-</td><td>-</td><td>-</td><td>31.02</td></tr><tr><td>Undisputed dues - Others</td><td>410.04</td><td>106.87</td><td>-</td><td>-</td><td>516.91</td></tr><tr><td>Disputed dues - MSME</td><td>-</td><td>-</td><td>-</td><td>-</td><td>-</td></tr><tr><td>Disputed dues - Others</td><td>-</td><td>-</td><td>-</td><td>-</td><td>-</td></tr><tr><td></td><td>441.06</td><td>106.87</td><td>-</td><td>-</td><td>547.93</td></tr></tbody></table>"}, {"bbox": [81, 1202, 394, 1220], "category": "Section-header", "text": "### Micro, small and medium enterprise"}, {"bbox": [81, 1222, 1279, 1241], "category": "Text", "text": "Disclosure in respect to Micro and Small Enterprises as per Micro, Small and Medium Enterprises Development Act, 2006 ('MSMED') Act, 2006 is as follows:"}, {"bbox": [81, 1264, 1600, 1319], "category": "Text", "text": "The information as required under Micro, Small and Medium Enterprises Development Act, 2006, has been determined to the extent such parties have been identified on the basis of information available with the Company and relied upon by the auditors. The principal amounts / interest payable amounts for delayed payments to such vendors as at Balance Sheet date during the current year and previous year mentioned below"}, {"bbox": [76, 1333, 1445, 1776], "category": "Table", "text": "<table><thead><tr><th>Particulars</th><th>As at<br>31-Mar-25</th><th>As at<br>31-Mar-24</th><th>As at<br>31-Mar-23</th></tr></thead><tbody><tr><td>The principal amount remaining unpaid to any supplier registered under the Micro, Small and Medium Enterprises Development Act, 2006 and remaining unpaid as at the year end.</td><td>38.69</td><td>20.41</td><td>31.02</td></tr><tr><td>Principal amount paid to suppliers registered under the MSMED Act, beyond the appointed day during the year.</td><td>-</td><td>-</td><td>-</td></tr><tr><td>Interest paid, other than under section 16 of MSMED Act, to suppliers registered under the MSMED Act, beyond the appointed day during the year.</td><td>-</td><td>-</td><td>-</td></tr><tr><td>Interest paid, under section 16 of MSMED Act, to suppliers registered under the MSMED Act, beyond the appointed day during the year</td><td>-</td><td>-</td><td>-</td></tr><tr><td>Amount of interest accrued and remaining unpaid for the year.</td><td>-</td><td>-</td><td>-</td></tr><tr><td>The amount of interest accrued and remaining unpaid at the end of each accounting year.</td><td>-</td><td>-</td><td>-</td></tr><tr><td>The amount of further interest due and payable even in the succeeding years, until such date when the interest dues as above are actually paid to the small enterprise, for the purpose of disallowance as a deductible expenditure under section 23.</td><td>-</td><td>-</td><td>-</td></tr></tbody></table>"}, {"bbox": [49, 1838, 444, 1856], "category": "Section-header", "text": "## 21. OTHER CURRENT FINANCIAL LIABILITIES"}, {"bbox": [76, 1856, 1445, 2004], "category": "Table", "text": "<table><thead><tr><th>Particulars</th><th>As at<br>31-Mar-25</th><th>As at<br>31-Mar-24</th><th>As at<br>31-Mar-23</th></tr></thead><tbody><tr><td>Deposits</td><td>18.01</td><td>14.70</td><td>14.70</td></tr><tr><td>Payable to employees</td><td>19.09</td><td>19.48</td><td>12.23</td></tr><tr><td>Expenses Payable</td><td>49.59</td><td>18.09</td><td>13.63</td></tr><tr><td></td><td>86.70</td><td>52.27</td><td>40.56</td></tr></tbody></table>"}, {"bbox": [49, 2046, 341, 2064], "category": "Section-header", "text": "## 22. OTHER CURRENT LIABILITIES"}, {"bbox": [76, 2083, 1445, 2189], "category": "Table", "text": "<table><thead><tr><th>Particulars</th><th>As at<br>31-Mar-25</th><th>As at<br>31-Mar-24</th><th>As at<br>31-Mar-23</th></tr></thead><tbody><tr><td>Statutory dues (including provident fund, tax deducted at source and others)</td><td>102.56</td><td>60.50</td><td>5.98</td></tr><tr><td></td><td>102.56</td><td>60.50</td><td>5.98</td></tr></tbody></table>"}, {"bbox": [800, 2239, 850, 2266], "category": "Page-footer", "text": "216"}]